{
  "id": "search_general_procedure_3_1754045837",
  "title": "Defense Function",
  "content": "... criminal client can be protected and preserved only by prompt legal action. Defense counsel should inform the client of his or her rights in the criminal ...",
  "source": "Web Search",
  "source_url": "https://www.americanbar.org/groups/criminal_justice/resources/standards/defense-function/",
  "jurisdiction": "general",
  "legal_domain": "constitutional_law",
  "document_type": "procedure",
  "metadata": {
    "search_query": "legal procedures criminal defense",
    "search_rank": 4,
    "snippet": "... criminal client can be protected and preserved only by prompt legal action. Defense counsel should inform the client of his or her rights in the criminal ..."
  },
  "created_at": "2025-08-01T10:57:17.549008",
  "content_hash": "77da7b70c9e61953ea3cd39bbbc51c51"
}