{
  "id": "search_india_central_statute_0_1754045335",
  "title": "Companies Act, 2013",
  "content": "CHAPTER I. PRELIMINARY. SECTIONS. 1. Short title, extent, commencement and application. 2. Definitions. CHAPTER II.",
  "source": "Web Search",
  "source_url": "https://www.indiacode.nic.in/bitstream/123456789/2114/5/A2013-18.pdf",
  "jurisdiction": "india_central",
  "legal_domain": "general_law",
  "document_type": "statute",
  "metadata": {
    "search_query": "site:indiacode.nic.in Indian Companies Act 2013",
    "search_rank": 1,
    "snippet": "CHAPTER I. PRELIMINARY. SECTIONS. 1. Short title, extent, commencement and application. 2. Definitions. CHAPTER II."
  },
  "created_at": "2025-08-01T10:48:55.013422",
  "content_hash": "39a7d9412b3cefa21cd24ac3f6a2e963"
}